odoo8_addon_base_mail_bcc-8.0.1.0.0-py2.7-nspkg.pth
odoo8_addon_base_mail_bcc-8.0.1.0.0.dist-info/DESCRIPTION.rst
odoo8_addon_base_mail_bcc-8.0.1.0.0.dist-info/METADATA
odoo8_addon_base_mail_bcc-8.0.1.0.0.dist-info/RECORD
odoo8_addon_base_mail_bcc-8.0.1.0.0.dist-info/WHEEL
odoo8_addon_base_mail_bcc-8.0.1.0.0.dist-info/metadata.json
odoo8_addon_base_mail_bcc-8.0.1.0.0.dist-info/namespace_packages.txt
odoo8_addon_base_mail_bcc-8.0.1.0.0.dist-info/top_level.txt
odoo_addons/base_mail_bcc/README.rst
odoo_addons/base_mail_bcc/__init__.py
odoo_addons/base_mail_bcc/__openerp__.py
odoo_addons/base_mail_bcc/demo/mail_bcc_demo.xml
odoo_addons/base_mail_bcc/models/__init__.py
odoo_addons/base_mail_bcc/models/ir_mail_server.py
odoo_addons/base_mail_bcc/tests/__init__.py
odoo_addons/base_mail_bcc/tests/test_base_mail_bcc.py
